andrewAudio/__init__.py
andrewAudio-1.0.3.dist-info/LICENSE
andrewAudio-1.0.3.dist-info/METADATA
andrewAudio-1.0.3.dist-info/WHEEL
andrewAudio-1.0.3.dist-info/top_level.txt
andrewAudio-1.0.3.dist-info/RECORD
