Metadata-Version: 2.1
Name: andrewAudio
Version: 1.0.3
Summary: A sound-object labelling machine learning model for use with Audacity. Uses VGGish for feature extraction and a Pytorch N-way classifier neural network for training.
Home-page: https://github.com/andrew-audio/andrew-model
Author: Cooper Barth & Jack Wiig
Author-email: cooperfbarth@gmail.com
License: MIT
Platform: UNKNOWN
Classifier: Programming Language :: Python :: 3
Classifier: License :: OSI Approved :: MIT License
Classifier: Operating System :: OS Independent
Requires-Dist: numpy
Requires-Dist: pysoundfile
Requires-Dist: resampy
Requires-Dist: scikit-learn
Requires-Dist: scipy
Requires-Dist: six
Requires-Dist: tensorflow
Requires-Dist: torch
